License.txt
README.md
setup.cfg
setup.py
pycamdetector/ClassificationModule.py
pycamdetector/ColorModule.py
pycamdetector/FPS.py
pycamdetector/FaceDetectionModule.py
pycamdetector/FaceMeshModule.py
pycamdetector/HandTrackingModule.py
pycamdetector/ObjectDetectionModule.py
pycamdetector/PlotModule.py
pycamdetector/PoseModule.py
pycamdetector/SerialModule.py
pycamdetector/Utils.py
pycamdetector/__init__.py
pycamdetector.egg-info/PKG-INFO
pycamdetector.egg-info/SOURCES.txt
pycamdetector.egg-info/dependency_links.txt
pycamdetector.egg-info/requires.txt
pycamdetector.egg-info/top_level.txt