Metadata-Version: 2.1
Name: pycamdetector
Version: 0.6.5
Summary: Advanced Computer Vision Library which includes Face Detection, Hand Detection, Pose Estimation, Object Detection
Home-page: https://github.com/roshaan55/pycamdetector
Download-URL: https://github.com/roshaan55/pycamdetector/archive/refs/tags/v_0.6.2.tar.gz
Author: Roshaan Mehmood
Author-email: roshaan55@gmail.com
License: MIT
Keywords: pycamdetector,handtracking,facelandmarks,pose-estimation,object-detection,face-detection
Classifier: Development Status :: 3 - Alpha
Classifier: Intended Audience :: Developers
Classifier: Topic :: Software Development :: Build Tools
Classifier: License :: OSI Approved :: MIT License
Classifier: Programming Language :: Python :: 3.6
Classifier: Programming Language :: Python :: 3.7
Classifier: Programming Language :: Python :: 3.8
Classifier: Programming Language :: Python :: 3.9
License-File: License.txt
